zipbiaschecker/__init__.py
zipbiaschecker/zipbiaschecker.py
zipbiaschecker/data/__init__.py
zipbiaschecker/data/example/__init__.py
zipbiaschecker/data/original/__init__.py
zipbiaschecker/data/processed/__init__.py
zipbiaschecker/images/__init__.py
zipbiaschecker/tests/__init__.py
zipbiaschecker/tests/check_bias_test.py
zipbiaschecker-0.0.1.dist-info/LICENSE.txt
zipbiaschecker-0.0.1.dist-info/METADATA
zipbiaschecker-0.0.1.dist-info/WHEEL
zipbiaschecker-0.0.1.dist-info/top_level.txt
zipbiaschecker-0.0.1.dist-info/RECORD
