Metadata-Version: 2.1
Name: zipbiaschecker
Version: 0.0.1
Summary: A quick check for racial bias using zipcode-level Census data
Home-page: https://github.com/edjzhang/zipbiaschecker
Author: Edwin Zhang
License: UNKNOWN
Platform: UNKNOWN
Classifier: Programming Language :: Python :: 3
Classifier: License :: OSI Approved :: MIT License
Classifier: Operating System :: OS Independent
